MANIFEST.in
README.rst
requirements.txt
setup.cfg
setup.py
djmicrosip_facturacion/__init__.py
djmicrosip_facturacion/__init__.pyc
djmicrosip_facturacion/config.pyc
djmicrosip_facturacion/forms.pyc
djmicrosip_facturacion/models.pyc
djmicrosip_facturacion/urls.pyc
djmicrosip_facturacion/views.pyc
djmicrosip_facturacion.egg-info/PKG-INFO
djmicrosip_facturacion.egg-info/SOURCES.txt
djmicrosip_facturacion.egg-info/dependency_links.txt
djmicrosip_facturacion.egg-info/requires.txt
djmicrosip_facturacion.egg-info/top_level.txt
djmicrosip_facturacion/static/djmicrosip_facturacion/facturas/CG0000148.ini.pdf
djmicrosip_facturacion/static/djmicrosip_facturacion/facturas/CG0000156.ini.pdf
djmicrosip_facturacion/static/djmicrosip_facturacion/facturas/CG0000157.ini.pdf
djmicrosip_facturacion/static/djmicrosip_facturacion/facturas/CG0000158.ini.pdf
djmicrosip_facturacion/static/djmicrosip_facturacion/facturas/CG0000159.ini.pdf
djmicrosip_facturacion/static/djmicrosip_facturacion/js/facturacion.js
djmicrosip_facturacion/templates/djmicrosip_facturacion/base.html
djmicrosip_facturacion/templates/djmicrosip_facturacion/facturar.html
djmicrosip_facturacion/templates/djmicrosip_facturacion/index.html